opla/__init__.py
opla/__main__.py
opla/bibliography.py
opla/opla.py
opla/parse.py
opla/payload.py
opla/shortcodes.py
opla/templating.py
opla/themes/base/templates/base.html.j2
opla/themes/base/templates/macro.j2
opla/themes/base/templates/partials/content.html.j2
opla/themes/base/templates/partials/favicon.html.j2
opla/themes/base/templates/partials/footer.html.j2
opla/themes/base/templates/partials/footer_contact.html.j2
opla/themes/base/templates/partials/footer_generated_by.html.j2
opla/themes/base/templates/partials/footer_social.html.j2
opla/themes/base/templates/partials/header.html.j2
opla/themes/base/templates/partials/script.html.j2
opla/themes/base/templates/partials/style.html.j2
opla/themes/materialize/static/css/materialize.css
opla/themes/materialize/static/css/materialize.min.css
opla/themes/materialize/static/css/style.css
opla/themes/materialize/static/js/materialize.js
opla/themes/materialize/static/js/materialize.min.js
opla/themes/materialize/templates/index.html.j2
opla/themes/materialize/templates/partials/footer_generated_by.html.j2
opla/themes/materialize/templates/partials/header.html.j2
opla/themes/materialize/templates/partials/script_materialize.html.j2
opla/themes/rawhtml/templates/index.html.j2
opla/themes/water/static/css/style.css
opla/themes/water/templates/index.html.j2
opla_ssg-1.1.6.dist-info/licenses/LICENSE
opla_ssg-1.1.6.dist-info/METADATA
opla_ssg-1.1.6.dist-info/WHEEL
opla_ssg-1.1.6.dist-info/entry_points.txt
opla_ssg-1.1.6.dist-info/top_level.txt
opla_ssg-1.1.6.dist-info/RECORD
