Metadata-Version: 2.4
Name: opla-ssg
Version: 1.1.6
Summary: A personal webpage generator
Author-email: IRMA <matthieu.boileau@math.unistra.fr>
License: MIT
Project-URL: Homepage, https://gitlab.math.unistra.fr/irma/opla
Classifier: Programming Language :: Python :: 3
Classifier: License :: OSI Approved :: MIT License
Classifier: Operating System :: OS Independent
Requires-Python: >=3.9
License-File: LICENSE
Requires-Dist: mdslicer
Requires-Dist: markdown_link_attr_modifier
Requires-Dist: shortcodes
Requires-Dist: jinja2
Requires-Dist: pybtex>=0.25.0
Requires-Dist: setuptools
Provides-Extra: test
Requires-Dist: pytest; extra == "test"
Requires-Dist: pytest-cov; extra == "test"
Requires-Dist: pytest-mock; extra == "test"
Requires-Dist: faker; extra == "test"
Provides-Extra: doc
Requires-Dist: Sphinx>=7.2.2; extra == "doc"
Requires-Dist: myst-parser; extra == "doc"
Requires-Dist: furo; extra == "doc"
Requires-Dist: sphinx-copybutton; extra == "doc"
Requires-Dist: sphinx-autobuild; extra == "doc"
Requires-Dist: sphinx_design; extra == "doc"
Dynamic: license-file
